setup.py
teleflask/__init__.py
teleflask/messages.py
teleflask.egg-info/PKG-INFO
teleflask.egg-info/SOURCES.txt
teleflask.egg-info/dependency_links.txt
teleflask.egg-info/requires.txt
teleflask.egg-info/top_level.txt
teleflask/server/__init__.py
teleflask/server/base.py
teleflask/server/extras.py
teleflask/server/mixins.py
teleflask/server/utilities.py