Metadata-Version: 1.1
Name: teleflask
Version: 0.0.4
Summary: Easily create Telegram bots with pytgbot and flask. Webhooks made easy.
Home-page: https://github.com/luckydonald/teleflask
Author: luckydonald
Author-email: code@luckydonald.de
License: GPLv3+
Keywords: pytgbot flask webhook telegram bot api python message send receive python secure fast answer reply image voice picture location contacts typing multi messanger inline quick reply gif image video mp4 mpeg4
Platform: UNKNOWN
Classifier: Development Status :: 2 - Pre-Alpha
Classifier: Intended Audience :: Developers
Classifier: Topic :: Communications
Classifier: Topic :: Communications :: Chat
Classifier: Topic :: Multimedia
Classifier: Topic :: Software Development :: Libraries
Classifier: Topic :: Software Development :: Libraries :: Python Modules
Classifier: Environment :: Web Environment
Classifier: Framework :: Flask
Classifier: License :: OSI Approved :: GNU General Public License v3 or later (GPLv3+)
Classifier: Programming Language :: Python :: 2.7
Classifier: Programming Language :: Python :: 3
Classifier: Programming Language :: Python :: 3.4
Classifier: Operating System :: MacOS :: MacOS X
Classifier: Operating System :: Unix
